<TcMenuPlugin name="Serve up embedCONTROL JS from webserver" id="36f98a10-7ffc-468c-8b6b-3961b5c87cbe" subsystem="REMOTE"
              xmlns="https://www.thecoderscorner.com/libraries/tcmenuPluginItem" xmlns:xsi="http://www.w3.org/2001/XMLSchema-instance"
              xsi:schemaLocation="https://www.thecoderscorner.com/libraries/tcmenuPluginItem https://www.thecoderscorner.com/libraries/tcmenu-plugin-item.xsd">
    <SupportedPlatforms>
        <Platform>RASPBERRY_PIJ</Platform>
    </SupportedPlatforms>
    <Description>Control your embedded device remotely using embedCONTROL JS served up using a lightweight webserver.</Description>
    <Documentation link="https://www.thecoderscorner.com/products/arduino-libraries/tc-menu/embedded_java_raspberru_pi/"/>
    <RequiredLibraries/>
    <ImageFile>embedCONTROL.png</ImageFile>

    <Properties>
        <Property id="EJ_WEB_SERVER_PORT" name="HTTP port to listen on" initial="8080" type="int"
                  desc="Port on which to listen for HTTP requests, to listen on port 80 we recommend a proxy"/>
        <Property id="EJ_WEB_SOCKET_PORT" name="HTTP web socket port" initial="8083" type="int"
                  desc="Port on which to listen for web socket data"/>
    </Properties>

    <ApplicabilityDefs/>

    <SourceFiles>
    </SourceFiles>

    <IncludeFiles/>

    <GlobalVariables>
        <Variable name="tagVal" type="TagValMenuCommandProtocol" inContext="true"/>

        <Variable name="webSockets" type="WebSocketServerConnectionManager" export="true">
            <Param ref="TagValMenuCommandProtocol" name="protocol"/>
            <Param value="${EJ_WEB_SOCKET_PORT}" name="wsPort"/>
            <Param ref="Clock" name="clock"/>
        </Variable>
    </GlobalVariables>

    <SetupFunctions>

    </SetupFunctions>
</TcMenuPlugin>